{
  "fetched_at": "2026-07-20T07:08:09.969782+00:00",
  "region": "germanynorth",
  "currencies": {
    "NOK": {
      "vm_prices": {
        "Standard_D8s_v5": {
          "linux_payg": 5.937482,
          "windows_payg": 9.591317,
          "linux_1yr": 3.663265388127854,
          "linux_3yr": 2.3454570471841705,
          "windows_1yr": 7.317100388127853,
          "windows_3yr": 5.99929204718417
        },
        "Standard_D48s_v5": {
          "linux_payg": 35.624893,
          "windows_payg": 57.547904,
          "linux_1yr": 21.980725764840184,
          "linux_3yr": 14.071986659056318,
          "windows_1yr": 43.90373676484019,
          "windows_3yr": 35.994997659056324
        },
        "Standard_D96s_v5": {
          "windows_payg": 115.095809,
          "linux_payg": 71.249786,
          "linux_1yr": 43.96145152968037,
          "linux_3yr": 28.14359550608828,
          "windows_1yr": 87.80747452968038,
          "windows_3yr": 71.98961850608828
        },
        "Standard_D32s_v5": {
          "windows_payg": 38.36527,
          "linux_payg": 23.749929,
          "linux_1yr": 14.654194988584475,
          "linux_3yr": 9.381072564687976,
          "windows_1yr": 29.269535988584476,
          "windows_3yr": 23.996413564687977
        },
        "Standard_D4s_v5": {
          "linux_payg": 2.968741,
          "windows_payg": 4.795659,
          "linux_1yr": 1.831632694063927,
          "linux_3yr": 1.1727285235920852,
          "windows_1yr": 3.6585506940639263,
          "windows_3yr": 2.9996465235920846
        },
        "Standard_D2s_v5": {
          "linux_payg": 1.489335,
          "windows_payg": 2.402794,
          "linux_1yr": 0.9158163470319635,
          "linux_3yr": 0.5863642617960426,
          "windows_1yr": 1.8292753470319636,
          "windows_3yr": 1.4998232617960428
        },
        "Standard_D64s_v5": {
          "windows_payg": 76.730539,
          "linux_payg": 47.499858,
          "linux_1yr": 29.30725654109589,
          "linux_3yr": 18.762522941400306,
          "windows_1yr": 58.53793754109588,
          "windows_3yr": 47.993203941400296
        },
        "Standard_D16s_v5": {
          "linux_payg": 11.874964,
          "windows_payg": 19.182635,
          "linux_1yr": 7.326530776255708,
          "linux_3yr": 4.690536282343988,
          "windows_1yr": 14.634201776255708,
          "windows_3yr": 11.998207282343989
        },
        "Standard_E2s_v5": {
          "linux_payg": 1.965922,
          "windows_payg": 2.879381,
          "linux_1yr": 1.2105097260273971,
          "linux_3yr": 0.7748924619482497,
          "windows_1yr": 2.123968726027397,
          "windows_3yr": 1.6883514619482498
        },
        "Standard_E8s_v5": {
          "linux_payg": 7.843831,
          "windows_payg": 11.497666,
          "linux_1yr": 4.842038904109589,
          "linux_3yr": 3.0999476598173517,
          "windows_1yr": 8.49587390410959,
          "windows_3yr": 6.753782659817352
        },
        "Standard_E4s_v5": {
          "linux_payg": 3.921915,
          "windows_payg": 5.748833,
          "linux_1yr": 2.4210194520547943,
          "linux_3yr": 1.5497849238964994,
          "windows_1yr": 4.247937452054795,
          "windows_3yr": 3.3767029238964996
        },
        "Standard_E48s_v5": {
          "windows_payg": 69.005855,
          "linux_payg": 47.082844,
          "linux_1yr": 29.052233424657533,
          "linux_3yr": 18.599308146879757,
          "windows_1yr": 50.97524442465753,
          "windows_3yr": 40.52231914687975
        },
        "Standard_E64s_v5": {
          "windows_payg": 92.011116,
          "linux_payg": 62.780435,
          "linux_1yr": 38.73631123287671,
          "linux_3yr": 24.79920346651446,
          "windows_1yr": 67.96699223287672,
          "windows_3yr": 54.02988446651446
        },
        "Standard_E96s_v5": {
          "windows_payg": 138.021639,
          "linux_payg": 94.175616,
          "linux_1yr": 58.10560028538813,
          "linux_3yr": 37.198616293759514,
          "windows_1yr": 101.95162328538811,
          "windows_3yr": 81.0446392937595
        },
        "Standard_E20s_v5": {
          "windows_payg": 28.754094,
          "linux_payg": 19.619506,
          "linux_1yr": 12.105097260273974,
          "linux_3yr": 7.749680243531202,
          "windows_1yr": 21.239685260273973,
          "windows_3yr": 16.8842682435312
        },
        "Standard_E32s_v5": {
          "linux_payg": 31.395182,
          "windows_payg": 46.010523,
          "linux_1yr": 19.368155616438354,
          "linux_3yr": 12.399412827245055,
          "windows_1yr": 33.98349661643836,
          "windows_3yr": 27.014753827245055
        },
        "Standard_E16s_v5": {
          "linux_payg": 15.697591,
          "windows_payg": 23.005261,
          "linux_1yr": 9.684077808219177,
          "linux_3yr": 6.199895319634703,
          "windows_1yr": 16.99174780821918,
          "windows_3yr": 13.507565319634704
        }
      },
      "disk_prices": {
        "premium-ssd": {
          "P20": 55.125253,
          "P3": 2.015567,
          "P15": 30.620728,
          "P10": 15.270648,
          "P4": 4.358787,
          "P1": 0.503395,
          "P30": 110.240577,
          "P80": 3674.785179,
          "P70": 1837.442234,
          "P40": 220.491082,
          "Burst Enablement": 412.377004,
          "Snapshots": 1.876562,
          "P50": 428.729902,
          "Burst Transactions": 0.083899,
          "P6": 7.883547,
          "P2": 1.002819,
          "Confidential Compute Encryption": 0.000457,
          "P60": 857.449875
        },
        "standard-ssd": {
          "E30": 0.019858,
          "E50": 0.019858,
          "E20": 0.019858,
          "E4": 0.019858,
          "E10": 0.019858,
          "E60": 0.019858,
          "E80": 0.019858,
          "E40": 0.019858,
          "E3": 2.015567,
          "E6": 0.019858,
          "E2": 1.002819,
          "E15": 0.019858,
          "E70": 0.019858,
          "E1": 0.503395,
          "Confidential Compute Encryption": 0.000318,
          "Snapshots": 1.876562,
          "Disk Transactions": 0.03356
        },
        "standard-hdd": {
          "S15": 0.004964,
          "S80": 0.004964,
          "S30": 0.004964,
          "S70": 0.004964,
          "S10": 0.004964,
          "S4": 0.004964,
          "S20": 0.004964,
          "Disk Transactions": 0.00839,
          "S50": 0.004964,
          "S6": 0.004964,
          "S60": 0.004964,
          "S40": 0.004964,
          "Snapshots": 0.645378,
          "Standard HDD Managed Disks - Confidential Compute Encryption": 0.000129
        }
      }
    },
    "EUR": {
      "vm_prices": {
        "Standard_D8s_v5": {
          "linux_payg": 0.524792,
          "windows_payg": 0.84774,
          "linux_1yr": 0.3237821602739726,
          "linux_3yr": 0.2073060696347032,
          "windows_1yr": 0.6467301602739726,
          "windows_3yr": 0.5302540696347032
        },
        "Standard_D48s_v5": {
          "linux_payg": 3.148749,
          "windows_payg": 5.086441,
          "linux_1yr": 1.9427931421232876,
          "linux_3yr": 1.2437696311263318,
          "windows_1yr": 3.8804851421232875,
          "windows_3yr": 3.1814616311263313
        },
        "Standard_D96s_v5": {
          "windows_payg": 10.172883,
          "linux_payg": 6.297499,
          "linux_1yr": 3.88558628413242,
          "linux_3yr": 2.487505868873668,
          "windows_1yr": 7.76097028413242,
          "windows_3yr": 6.362889868873669
        },
        "Standard_D32s_v5": {
          "windows_payg": 3.390961,
          "linux_payg": 2.099166,
          "linux_1yr": 1.2952288214611873,
          "linux_3yr": 0.8291574918188737,
          "windows_1yr": 2.5870238214611874,
          "windows_3yr": 2.1209524918188736
        },
        "Standard_D4s_v5": {
          "linux_payg": 0.262396,
          "windows_payg": 0.42387,
          "linux_1yr": 0.1618910801369863,
          "linux_3yr": 0.1036530348173516,
          "windows_1yr": 0.3233650801369863,
          "windows_3yr": 0.2651270348173516
        },
        "Standard_D2s_v5": {
          "linux_payg": 0.131637,
          "windows_payg": 0.212374,
          "linux_1yr": 0.08094554006849315,
          "linux_3yr": 0.051826517427701675,
          "windows_1yr": 0.16168254006849314,
          "windows_3yr": 0.13256351742770167
        },
        "Standard_D64s_v5": {
          "windows_payg": 6.781922,
          "linux_payg": 4.198333,
          "linux_1yr": 2.590357462671233,
          "linux_3yr": 1.6583483770547944,
          "windows_1yr": 5.173946462671233,
          "windows_3yr": 4.241937377054795
        },
        "Standard_D16s_v5": {
          "linux_payg": 1.049583,
          "windows_payg": 1.69548,
          "linux_1yr": 0.6475643206621005,
          "linux_3yr": 0.4145787459284627,
          "windows_1yr": 1.2934613206621006,
          "windows_3yr": 1.0604757459284628
        },
        "Standard_E2s_v5": {
          "linux_payg": 0.17376,
          "windows_payg": 0.254498,
          "linux_1yr": 0.10699237226027397,
          "linux_3yr": 0.06848981133942161,
          "windows_1yr": 0.18773037226027398,
          "windows_3yr": 0.14922781133942162
        },
        "Standard_E8s_v5": {
          "linux_payg": 0.693287,
          "windows_payg": 1.016235,
          "linux_1yr": 0.4279694891552511,
          "linux_3yr": 0.2739926387747337,
          "windows_1yr": 0.7509174891552511,
          "windows_3yr": 0.5969406387747337
        },
        "Standard_E4s_v5": {
          "linux_payg": 0.346643,
          "windows_payg": 0.508118,
          "linux_1yr": 0.21398474452054794,
          "linux_3yr": 0.13697962267884323,
          "windows_1yr": 0.3754597445205479,
          "windows_3yr": 0.2984546226788432
        },
        "Standard_E48s_v5": {
          "windows_payg": 6.099166,
          "linux_payg": 4.161474,
          "linux_1yr": 2.5678169348173516,
          "linux_3yr": 1.6439224392313547,
          "windows_1yr": 4.505508934817351,
          "windows_3yr": 3.581614439231355
        },
        "Standard_E64s_v5": {
          "windows_payg": 8.132514,
          "linux_payg": 5.548925,
          "linux_1yr": 3.423755913127854,
          "linux_3yr": 2.19190771674277,
          "windows_1yr": 6.007344913127855,
          "windows_3yr": 4.77549671674277
        },
        "Standard_E96s_v5": {
          "windows_payg": 12.19921,
          "linux_payg": 8.323826,
          "linux_1yr": 5.135734049771689,
          "linux_3yr": 3.2878448784246572,
          "windows_1yr": 9.011118049771689,
          "windows_3yr": 7.163228878424658
        },
        "Standard_E20s_v5": {
          "windows_payg": 2.541466,
          "linux_payg": 1.734094,
          "linux_1yr": 1.06992372283105,
          "linux_3yr": 0.6849649002283105,
          "windows_1yr": 1.8772957228310498,
          "windows_3yr": 1.4923369002283102
        },
        "Standard_E32s_v5": {
          "linux_payg": 2.774901,
          "windows_payg": 4.066696,
          "linux_1yr": 1.7118779566210045,
          "linux_3yr": 1.0959371616818874,
          "windows_1yr": 3.003672956621005,
          "windows_3yr": 2.387732161681888
        },
        "Standard_E16s_v5": {
          "linux_payg": 1.387451,
          "windows_payg": 2.033348,
          "linux_1yr": 0.8559389783105023,
          "linux_3yr": 0.5479852775114156,
          "windows_1yr": 1.5018359783105024,
          "windows_3yr": 1.1938822775114157
        }
      },
      "disk_prices": {
        "premium-ssd": {
          "P20": 4.872312,
          "P3": 0.178148,
          "P15": 2.70645,
          "P10": 1.349715,
          "P4": 0.385257,
          "P1": 0.044493,
          "P30": 9.743747,
          "P80": 324.800351,
          "P70": 162.404563,
          "P40": 19.488372,
          "Burst Enablement": 36.448442,
          "Snapshots": 0.165862,
          "P50": 37.893813,
          "Burst Transactions": 0.007416,
          "P6": 0.696797,
          "P2": 0.088635,
          "Confidential Compute Encryption": 4e-05,
          "P60": 75.786749
        },
        "standard-ssd": {
          "E30": 0.001755,
          "E50": 0.001755,
          "E20": 0.001755,
          "E4": 0.001755,
          "E10": 0.001755,
          "E60": 0.001755,
          "E80": 0.001755,
          "E40": 0.001755,
          "E3": 0.178148,
          "E6": 0.001755,
          "E2": 0.088635,
          "E15": 0.001755,
          "E70": 0.001755,
          "E1": 0.044493,
          "Confidential Compute Encryption": 2.8e-05,
          "Snapshots": 0.165862,
          "Disk Transactions": 0.002966
        },
        "standard-hdd": {
          "S15": 0.000439,
          "S80": 0.000439,
          "S30": 0.000439,
          "S70": 0.000439,
          "S10": 0.000439,
          "S4": 0.000439,
          "S20": 0.000439,
          "Disk Transactions": 0.000742,
          "S50": 0.000439,
          "S6": 0.000439,
          "S60": 0.000439,
          "S40": 0.000439,
          "Snapshots": 0.057043,
          "Standard HDD Managed Disks - Confidential Compute Encryption": 1.1e-05
        }
      }
    },
    "SEK": {
      "vm_prices": {
        "Standard_D8s_v5": {
          "linux_payg": 5.816537,
          "windows_payg": 9.395944,
          "linux_1yr": 3.588645296803653,
          "linux_3yr": 2.297680487062405,
          "windows_1yr": 7.168052296803653,
          "windows_3yr": 5.877087487062404
        },
        "Standard_D48s_v5": {
          "linux_payg": 34.89922,
          "windows_payg": 56.375663,
          "linux_1yr": 21.532982128995435,
          "linux_3yr": 13.785342690258751,
          "windows_1yr": 43.00942512899544,
          "windows_3yr": 35.261785690258755
        },
        "Standard_D96s_v5": {
          "windows_payg": 112.751327,
          "linux_payg": 69.79844,
          "linux_1yr": 43.06596425799087,
          "linux_3yr": 27.570315264459666,
          "windows_1yr": 86.01885125799087,
          "windows_3yr": 70.52320226445967
        },
        "Standard_D32s_v5": {
          "windows_payg": 37.583776,
          "linux_payg": 23.266147,
          "linux_1yr": 14.355691535388129,
          "linux_3yr": 9.189981716133943,
          "windows_1yr": 28.67332053538813,
          "windows_3yr": 23.507610716133943
        },
        "Standard_D4s_v5": {
          "linux_payg": 2.908268,
          "windows_payg": 4.697972,
          "linux_1yr": 1.7943226484018264,
          "linux_3yr": 1.1488402435312024,
          "windows_1yr": 3.584026648401826,
          "windows_3yr": 2.9385442435312026
        },
        "Standard_D2s_v5": {
          "linux_payg": 1.458997,
          "windows_payg": 2.353849,
          "linux_1yr": 0.8971613242009132,
          "linux_3yr": 0.5744201217656012,
          "windows_1yr": 1.792013324200913,
          "windows_3yr": 1.4692721217656008
        },
        "Standard_D64s_v5": {
          "windows_payg": 75.167551,
          "linux_payg": 46.532294,
          "linux_1yr": 28.710272722602742,
          "linux_3yr": 18.380333548325723,
          "windows_1yr": 57.34552972260275,
          "windows_3yr": 47.015590548325726
        },
        "Standard_D16s_v5": {
          "linux_payg": 11.633073,
          "windows_payg": 18.791888,
          "linux_1yr": 7.177290593607306,
          "linux_3yr": 4.594990858066971,
          "windows_1yr": 14.336105593607307,
          "windows_3yr": 11.753805858066972
        },
        "Standard_E2s_v5": {
          "linux_payg": 1.925877,
          "windows_payg": 2.820728,
          "linux_1yr": 1.1858518493150685,
          "linux_3yr": 0.7591080346270929,
          "windows_1yr": 2.0807028493150685,
          "windows_3yr": 1.6539590346270927
        },
        "Standard_E8s_v5": {
          "linux_payg": 7.684053,
          "windows_payg": 11.263461,
          "linux_1yr": 4.743407397260274,
          "linux_3yr": 3.03680225456621,
          "windows_1yr": 8.322815397260275,
          "windows_3yr": 6.6162102545662105
        },
        "Standard_E4s_v5": {
          "linux_payg": 3.842027,
          "windows_payg": 5.63173,
          "linux_1yr": 2.371703698630137,
          "linux_3yr": 1.5182160692541857,
          "windows_1yr": 4.161406698630137,
          "windows_3yr": 3.307919069254186
        },
        "Standard_E48s_v5": {
          "windows_payg": 67.600217,
          "linux_payg": 46.123774,
          "linux_1yr": 28.460444383561644,
          "linux_3yr": 18.22044341133942,
          "windows_1yr": 49.93688738356165,
          "windows_3yr": 39.69688641133942
        },
        "Standard_E64s_v5": {
          "windows_payg": 90.136866,
          "linux_payg": 61.501608,
          "linux_1yr": 37.94725917808219,
          "linux_3yr": 24.294047920471844,
          "windows_1yr": 66.58251717808218,
          "windows_3yr": 52.92930592047185
        },
        "Standard_E96s_v5": {
          "windows_payg": 135.210162,
          "linux_payg": 92.257275,
          "linux_1yr": 56.9219991152968,
          "linux_3yr": 36.44088682267884,
          "windows_1yr": 99.87488611529679,
          "windows_3yr": 79.39377382267884
        },
        "Standard_E20s_v5": {
          "windows_payg": 28.168378,
          "linux_payg": 19.21986,
          "linux_1yr": 11.858518493150685,
          "linux_3yr": 7.5918205783866055,
          "windows_1yr": 20.807036493150683,
          "windows_3yr": 16.540338578386606
        },
        "Standard_E32s_v5": {
          "linux_payg": 30.755667,
          "windows_payg": 45.073296,
          "linux_1yr": 18.973629589041096,
          "linux_3yr": 12.146838902207003,
          "windows_1yr": 33.29125858904109,
          "windows_3yr": 26.464467902207005
        },
        "Standard_E16s_v5": {
          "linux_payg": 15.377834,
          "windows_payg": 22.536648,
          "linux_1yr": 9.486814794520548,
          "linux_3yr": 6.07360450913242,
          "windows_1yr": 16.645628794520547,
          "windows_3yr": 13.232418509132419
        }
      },
      "disk_prices": {
        "premium-ssd": {
          "P20": 54.002361,
          "P3": 1.97451,
          "P15": 29.996989,
          "P10": 14.959588,
          "P4": 4.269999,
          "P1": 0.493141,
          "P30": 107.994995,
          "P80": 3599.930431,
          "P70": 1800.013849,
          "P40": 215.999717,
          "Burst Enablement": 403.976954,
          "Snapshots": 1.838337,
          "P50": 419.996747,
          "Burst Transactions": 0.08219,
          "P6": 7.72296,
          "P2": 0.982392,
          "Confidential Compute Encryption": 0.000447,
          "P60": 839.983767
        },
        "standard-ssd": {
          "E30": 0.019453,
          "E50": 0.019453,
          "E20": 0.019453,
          "E4": 0.019453,
          "E10": 0.019453,
          "E60": 0.019453,
          "E80": 0.019453,
          "E40": 0.019453,
          "E3": 1.97451,
          "E6": 0.019453,
          "E2": 0.982392,
          "E15": 0.019453,
          "E70": 0.019453,
          "E1": 0.493141,
          "Confidential Compute Encryption": 0.000311,
          "Snapshots": 1.838337,
          "Disk Transactions": 0.032876
        },
        "standard-hdd": {
          "S15": 0.004863,
          "S80": 0.004863,
          "S30": 0.004863,
          "S70": 0.004863,
          "S10": 0.004863,
          "S4": 0.004863,
          "S20": 0.004863,
          "Disk Transactions": 0.008219,
          "S50": 0.004863,
          "S6": 0.004863,
          "S60": 0.004863,
          "S40": 0.004863,
          "Snapshots": 0.632232,
          "Standard HDD Managed Disks - Confidential Compute Encryption": 0.000126
        }
      }
    },
    "GBP": {
      "vm_prices": {
        "Standard_D8s_v5": {
          "linux_payg": 0.453047,
          "windows_payg": 0.731846,
          "linux_1yr": 0.2795179906392694,
          "linux_3yr": 0.1789653141171994,
          "windows_1yr": 0.5583169906392694,
          "windows_3yr": 0.4577643141171994
        },
        "Standard_D48s_v5": {
          "linux_payg": 2.718285,
          "windows_payg": 4.391075,
          "linux_1yr": 1.6771944280821918,
          "linux_3yr": 1.0737342283105022,
          "windows_1yr": 3.349984428082192,
          "windows_3yr": 2.746524228310502
        },
        "Standard_D96s_v5": {
          "windows_payg": 8.782151,
          "linux_payg": 5.43657,
          "linux_1yr": 3.354388856278539,
          "linux_3yr": 2.1474396284627093,
          "windows_1yr": 6.69996985627854,
          "windows_3yr": 5.493020628462711
        },
        "Standard_D32s_v5": {
          "windows_payg": 2.927384,
          "linux_payg": 1.81219,
          "linux_1yr": 1.118158446917808,
          "linux_3yr": 0.7158036001141552,
          "windows_1yr": 2.233352446917808,
          "windows_3yr": 1.8309976001141552
        },
        "Standard_D4s_v5": {
          "linux_payg": 0.226524,
          "windows_payg": 0.365923,
          "linux_1yr": 0.1397589953196347,
          "linux_3yr": 0.08948265703957381,
          "windows_1yr": 0.2791579953196347,
          "windows_3yr": 0.2288816570395738
        },
        "Standard_D2s_v5": {
          "linux_payg": 0.113641,
          "windows_payg": 0.18334,
          "linux_1yr": 0.06987949760273973,
          "linux_3yr": 0.04474132853881279,
          "windows_1yr": 0.13957849760273972,
          "windows_3yr": 0.11444032853881278
        },
        "Standard_D64s_v5": {
          "windows_payg": 5.854767,
          "linux_payg": 3.62438,
          "linux_1yr": 2.2362304093607306,
          "linux_3yr": 1.4316360283866059,
          "windows_1yr": 4.4666174093607305,
          "windows_3yr": 3.6620230283866055
        },
        "Standard_D16s_v5": {
          "linux_payg": 0.906095,
          "windows_payg": 1.463692,
          "linux_1yr": 0.5590359811643836,
          "linux_3yr": 0.3579018000380517,
          "windows_1yr": 1.1166329811643836,
          "windows_3yr": 0.9154988000380517
        },
        "Standard_E2s_v5": {
          "linux_payg": 0.150006,
          "windows_payg": 0.219705,
          "linux_1yr": 0.09236547465753425,
          "linux_3yr": 0.05912658816590564,
          "windows_1yr": 0.16206447465753426,
          "windows_3yr": 0.12882558816590564
        },
        "Standard_E8s_v5": {
          "linux_payg": 0.598508,
          "windows_payg": 0.877306,
          "linux_1yr": 0.3694618985159817,
          "linux_3yr": 0.23653518078386607,
          "windows_1yr": 0.6482598985159818,
          "windows_3yr": 0.515333180783866
        },
        "Standard_E4s_v5": {
          "linux_payg": 0.299254,
          "windows_payg": 0.438653,
          "linux_1yr": 0.18473094920091324,
          "linux_3yr": 0.1182531762937595,
          "windows_1yr": 0.3241299492009132,
          "windows_3yr": 0.25765217629375947
        },
        "Standard_E48s_v5": {
          "windows_payg": 5.265351,
          "linux_payg": 3.59256,
          "linux_1yr": 2.2167713907534248,
          "linux_3yr": 1.4191822565068493,
          "windows_1yr": 3.8895623907534245,
          "windows_3yr": 3.091973256506849
        },
        "Standard_E64s_v5": {
          "windows_payg": 7.02072,
          "linux_payg": 4.790333,
          "linux_1yr": 2.955695187671233,
          "linux_3yr": 1.8922526180745813,
          "windows_1yr": 5.186082187671232,
          "windows_3yr": 4.122639618074581
        },
        "Standard_E96s_v5": {
          "windows_payg": 10.53146,
          "linux_payg": 7.185878,
          "linux_1yr": 4.43362926609589,
          "linux_3yr": 2.8383645130136985,
          "windows_1yr": 7.779211266095889,
          "windows_3yr": 6.183946513013698
        },
        "Standard_E20s_v5": {
          "windows_payg": 2.194023,
          "linux_payg": 1.497026,
          "linux_1yr": 0.9236547461187214,
          "linux_3yr": 0.5913235378614916,
          "windows_1yr": 1.6206517461187215,
          "windows_3yr": 1.2883205378614917
        },
        "Standard_E32s_v5": {
          "linux_payg": 2.395545,
          "windows_payg": 3.510739,
          "linux_1yr": 1.4778475938356166,
          "linux_3yr": 0.9461118949391172,
          "windows_1yr": 2.5930415938356166,
          "windows_3yr": 2.0613058949391174
        },
        "Standard_E16s_v5": {
          "linux_payg": 1.197773,
          "windows_payg": 1.75537,
          "linux_1yr": 0.7389237969178083,
          "linux_3yr": 0.47307036156773213,
          "windows_1yr": 1.2965207969178083,
          "windows_3yr": 1.0306673615677322
        }
      },
      "disk_prices": {
        "premium-ssd": {
          "P20": 4.20622,
          "P3": 0.153794,
          "P15": 2.336452,
          "P10": 1.165196,
          "P4": 0.332588,
          "P1": 0.038411,
          "P30": 8.411682,
          "P80": 280.396985,
          "P70": 140.20228,
          "P40": 16.824122,
          "Burst Enablement": 31.465586,
          "Snapshots": 0.143187,
          "P50": 32.71336,
          "Burst Transactions": 0.006402,
          "P6": 0.601538,
          "P2": 0.076518,
          "Confidential Compute Encryption": 3.5e-05,
          "P60": 65.425963
        },
        "standard-ssd": {
          "E30": 0.001515,
          "E50": 0.001515,
          "E20": 0.001515,
          "E4": 0.001515,
          "E10": 0.001515,
          "E60": 0.001515,
          "E80": 0.001515,
          "E40": 0.001515,
          "E3": 0.153794,
          "E6": 0.001515,
          "E2": 0.076518,
          "E15": 0.001515,
          "E70": 0.001515,
          "E1": 0.038411,
          "Confidential Compute Encryption": 2.4e-05,
          "Snapshots": 0.143187,
          "Disk Transactions": 0.002561
        },
        "standard-hdd": {
          "S15": 0.000379,
          "S80": 0.000379,
          "S30": 0.000379,
          "S70": 0.000379,
          "S10": 0.000379,
          "S4": 0.000379,
          "S20": 0.000379,
          "Disk Transactions": 0.00064,
          "S50": 0.000379,
          "S6": 0.000379,
          "S60": 0.000379,
          "S40": 0.000379,
          "Snapshots": 0.049244,
          "Standard HDD Managed Disks - Confidential Compute Encryption": 1e-05
        }
      }
    },
    "USD": {
      "vm_prices": {
        "Standard_D8s_v5": {
          "linux_payg": 0.598,
          "windows_payg": 0.966,
          "linux_1yr": 0.3689497716894977,
          "linux_3yr": 0.23622526636225266,
          "windows_1yr": 0.7369497716894977,
          "windows_3yr": 0.6042252663622527
        },
        "Standard_D48s_v5": {
          "linux_payg": 3.588,
          "windows_payg": 5.796,
          "linux_1yr": 2.2138127853881278,
          "linux_3yr": 1.417275494672755,
          "windows_1yr": 4.421812785388128,
          "windows_3yr": 3.6252754946727554
        },
        "Standard_D96s_v5": {
          "windows_payg": 11.592,
          "linux_payg": 7.176,
          "linux_1yr": 4.4276255707762555,
          "linux_3yr": 2.8345129375951292,
          "windows_1yr": 8.843625570776256,
          "windows_3yr": 7.250512937595129
        },
        "Standard_D32s_v5": {
          "windows_payg": 3.864,
          "linux_payg": 2.392,
          "linux_1yr": 1.4759132420091323,
          "linux_3yr": 0.9448249619482496,
          "windows_1yr": 2.9479132420091325,
          "windows_3yr": 2.4168249619482496
        },
        "Standard_D4s_v5": {
          "linux_payg": 0.299,
          "windows_payg": 0.483,
          "linux_1yr": 0.18447488584474886,
          "linux_3yr": 0.11811263318112633,
          "windows_1yr": 0.36847488584474886,
          "windows_3yr": 0.30211263318112636
        },
        "Standard_D2s_v5": {
          "linux_payg": 0.15,
          "windows_payg": 0.242,
          "linux_1yr": 0.09223744292237443,
          "linux_3yr": 0.059056316590563165,
          "windows_1yr": 0.18423744292237443,
          "windows_3yr": 0.15105631659056318
        },
        "Standard_D64s_v5": {
          "windows_payg": 7.728,
          "linux_payg": 4.784,
          "linux_1yr": 2.9517123287671234,
          "linux_3yr": 1.8896879756468798,
          "windows_1yr": 5.895712328767123,
          "windows_3yr": 4.83368797564688
        },
        "Standard_D16s_v5": {
          "linux_payg": 1.196,
          "windows_payg": 1.932,
          "linux_1yr": 0.7378995433789954,
          "linux_3yr": 0.4724124809741248,
          "windows_1yr": 1.4738995433789954,
          "windows_3yr": 1.2084124809741248
        },
        "Standard_E2s_v5": {
          "linux_payg": 0.198,
          "windows_payg": 0.29,
          "linux_1yr": 0.12191780821917808,
          "linux_3yr": 0.0780441400304414,
          "windows_1yr": 0.21391780821917805,
          "windows_3yr": 0.17004414003044138
        },
        "Standard_E8s_v5": {
          "linux_payg": 0.79,
          "windows_payg": 1.158,
          "linux_1yr": 0.4876712328767123,
          "linux_3yr": 0.3122146118721461,
          "windows_1yr": 0.8556712328767122,
          "windows_3yr": 0.6802146118721459
        },
        "Standard_E4s_v5": {
          "linux_payg": 0.395,
          "windows_payg": 0.579,
          "linux_1yr": 0.24383561643835616,
          "linux_3yr": 0.1560882800608828,
          "windows_1yr": 0.4278356164383561,
          "windows_3yr": 0.34008828006088276
        },
        "Standard_E48s_v5": {
          "windows_payg": 6.95,
          "linux_payg": 4.742,
          "linux_1yr": 2.926027397260274,
          "linux_3yr": 1.8732496194824961,
          "windows_1yr": 5.134027397260274,
          "windows_3yr": 4.081249619482496
        },
        "Standard_E64s_v5": {
          "windows_payg": 9.267,
          "linux_payg": 6.323,
          "linux_1yr": 3.9013698630136986,
          "linux_3yr": 2.4976788432267885,
          "windows_1yr": 6.845369863013698,
          "windows_3yr": 5.4416788432267875
        },
        "Standard_E96s_v5": {
          "windows_payg": 13.901,
          "linux_payg": 9.485,
          "linux_1yr": 5.8521689497716896,
          "linux_3yr": 3.7464992389649923,
          "windows_1yr": 10.26816894977169,
          "windows_3yr": 8.162499238964992
        },
        "Standard_E20s_v5": {
          "windows_payg": 2.896,
          "linux_payg": 1.976,
          "linux_1yr": 1.2191780821917808,
          "linux_3yr": 0.780517503805175,
          "windows_1yr": 2.1391780821917807,
          "windows_3yr": 1.700517503805175
        },
        "Standard_E32s_v5": {
          "linux_payg": 3.162,
          "windows_payg": 4.634,
          "linux_1yr": 1.9506849315068493,
          "linux_3yr": 1.248820395738204,
          "windows_1yr": 3.4226849315068497,
          "windows_3yr": 2.7208203957382047
        },
        "Standard_E16s_v5": {
          "linux_payg": 1.581,
          "windows_payg": 2.317,
          "linux_1yr": 0.9753424657534246,
          "linux_3yr": 0.6244292237442922,
          "windows_1yr": 1.7113424657534249,
          "windows_3yr": 1.3604292237442923
        }
      },
      "disk_prices": {
        "premium-ssd": {
          "P20": 5.552,
          "P3": 0.203,
          "P15": 3.084,
          "P10": 1.538,
          "P4": 0.439,
          "P1": 0.0507,
          "P30": 11.103,
          "P80": 370.11,
          "P70": 185.06,
          "P40": 22.207,
          "Burst Enablement": 41.533,
          "Snapshots": 0.189,
          "P50": 43.18,
          "Burst Transactions": 0.00845,
          "P6": 0.794,
          "P2": 0.101,
          "Confidential Compute Encryption": 4.6e-05,
          "P60": 86.359
        },
        "standard-ssd": {
          "E30": 0.002,
          "E50": 0.002,
          "E20": 0.002,
          "E4": 0.002,
          "E10": 0.002,
          "E60": 0.002,
          "E80": 0.002,
          "E40": 0.002,
          "E3": 0.203,
          "E6": 0.002,
          "E2": 0.101,
          "E15": 0.002,
          "E70": 0.002,
          "E1": 0.0507,
          "Confidential Compute Encryption": 3.2e-05,
          "Snapshots": 0.189,
          "Disk Transactions": 0.00338
        },
        "standard-hdd": {
          "S15": 0.0005,
          "S80": 0.0005,
          "S30": 0.0005,
          "S70": 0.0005,
          "S10": 0.0005,
          "S4": 0.0005,
          "S20": 0.0005,
          "Disk Transactions": 0.000845,
          "S50": 0.0005,
          "S6": 0.0005,
          "S60": 0.0005,
          "S40": 0.0005,
          "Snapshots": 0.065,
          "Standard HDD Managed Disks - Confidential Compute Encryption": 1.3e-05
        }
      }
    },
    "DKK": {
      "vm_prices": {
        "Standard_D8s_v5": {
          "linux_payg": 3.922491,
          "windows_payg": 6.336332,
          "linux_1yr": 2.420070684931507,
          "linux_3yr": 1.549484200913242,
          "windows_1yr": 4.833911684931507,
          "windows_3yr": 3.963325200913242
        },
        "Standard_D48s_v5": {
          "linux_payg": 23.534948,
          "windows_payg": 38.017993,
          "linux_1yr": 14.521172893835617,
          "linux_3yr": 9.296406015981734,
          "windows_1yr": 29.004217893835616,
          "windows_3yr": 23.77945101598173
        },
        "Standard_D96s_v5": {
          "windows_payg": 76.035985,
          "linux_payg": 47.069896,
          "linux_1yr": 29.042345787671234,
          "linux_3yr": 18.59256243721461,
          "windows_1yr": 58.008434787671234,
          "windows_3yr": 47.55865143721461
        },
        "Standard_D32s_v5": {
          "windows_payg": 25.345328,
          "linux_payg": 15.689965,
          "linux_1yr": 9.681031523972603,
          "linux_3yr": 6.197437614155251,
          "windows_1yr": 19.3363945239726,
          "windows_3yr": 15.85280061415525
        },
        "Standard_D4s_v5": {
          "linux_payg": 1.961246,
          "windows_payg": 3.168166,
          "linux_1yr": 1.2100353424657535,
          "linux_3yr": 0.774742100456621,
          "windows_1yr": 2.4169553424657533,
          "windows_3yr": 1.9816621004566208
        },
        "Standard_D2s_v5": {
          "linux_payg": 0.983902,
          "windows_payg": 1.587363,
          "linux_1yr": 0.6050176712328768,
          "linux_3yr": 0.3873710502283105,
          "windows_1yr": 1.2084786712328768,
          "windows_3yr": 0.9908320502283106
        },
        "Standard_D64s_v5": {
          "windows_payg": 50.690657,
          "linux_payg": 31.37993,
          "linux_1yr": 19.36131426369863,
          "linux_3yr": 12.39512482305936,
          "windows_1yr": 38.67204126369863,
          "windows_3yr": 31.705851823059362
        },
        "Standard_D16s_v5": {
          "linux_payg": 7.844983,
          "windows_payg": 12.672664,
          "linux_1yr": 4.840141369863014,
          "linux_3yr": 3.0987188070776255,
          "windows_1yr": 9.667822369863014,
          "windows_3yr": 7.926399807077624
        },
        "Standard_E2s_v5": {
          "linux_payg": 1.298751,
          "windows_payg": 1.902211,
          "linux_1yr": 0.7997015753424658,
          "linux_3yr": 0.5119188299086758,
          "windows_1yr": 1.403161575342466,
          "windows_3yr": 1.1153788299086758
        },
        "Standard_E8s_v5": {
          "linux_payg": 5.181886,
          "windows_payg": 7.595727,
          "linux_1yr": 3.198806301369863,
          "linux_3yr": 2.047924914383562,
          "windows_1yr": 5.612647301369863,
          "windows_3yr": 4.4617659143835615
        },
        "Standard_E4s_v5": {
          "linux_payg": 2.590943,
          "windows_payg": 3.797864,
          "linux_1yr": 1.5994031506849316,
          "linux_3yr": 1.0238376598173515,
          "windows_1yr": 2.8063241506849312,
          "windows_3yr": 2.2307586598173517
        },
        "Standard_E48s_v5": {
          "windows_payg": 45.587482,
          "linux_payg": 31.104438,
          "linux_1yr": 19.192837808219178,
          "linux_3yr": 12.287299891552513,
          "windows_1yr": 33.67588180821918,
          "windows_3yr": 26.770343891552514
        },
        "Standard_E64s_v5": {
          "windows_payg": 60.785496,
          "linux_payg": 41.47477,
          "linux_1yr": 25.590450410958905,
          "linux_3yr": 16.383149720319636,
          "windows_1yr": 44.90117641095891,
          "windows_3yr": 35.69387572031964
        },
        "Standard_E96s_v5": {
          "windows_payg": 91.181524,
          "linux_payg": 62.215435,
          "linux_1yr": 38.38642440068493,
          "linux_3yr": 24.574599783105025,
          "windows_1yr": 67.35251340068493,
          "windows_3yr": 53.540688783105026
        },
        "Standard_E20s_v5": {
          "windows_payg": 18.995878,
          "linux_payg": 12.961276,
          "linux_1yr": 7.997015753424657,
          "linux_3yr": 5.119687488584475,
          "windows_1yr": 14.031617753424658,
          "windows_3yr": 11.154289488584476
        },
        "Standard_E32s_v5": {
          "linux_payg": 20.740665,
          "windows_payg": 30.396028,
          "linux_1yr": 12.795225205479452,
          "linux_3yr": 8.191450062785389,
          "windows_1yr": 22.450588205479455,
          "windows_3yr": 17.84681306278539
        },
        "Standard_E16s_v5": {
          "linux_payg": 10.370332,
          "windows_payg": 15.198014,
          "linux_1yr": 6.397612602739726,
          "linux_3yr": 4.095849828767124,
          "windows_1yr": 11.225294602739726,
          "windows_3yr": 8.923531828767125
        }
      },
      "disk_prices": {
        "premium-ssd": {
          "P20": 36.417511,
          "P3": 1.331548,
          "P15": 20.229035,
          "P10": 10.08828,
          "P4": 2.879555,
          "P1": 0.332559,
          "P30": 72.828463,
          "P80": 2427.681028,
          "P70": 1213.873311,
          "P40": 145.663485,
          "Burst Enablement": 272.429484,
          "Snapshots": 1.239717,
          "P50": 283.232733,
          "Burst Transactions": 0.055427,
          "P6": 5.208124,
          "P2": 0.662494,
          "Confidential Compute Encryption": 0.000302,
          "P60": 566.458907
        },
        "standard-ssd": {
          "E30": 0.013119,
          "E50": 0.013119,
          "E20": 0.013119,
          "E4": 0.013119,
          "E10": 0.013119,
          "E60": 0.013119,
          "E80": 0.013119,
          "E40": 0.013119,
          "E3": 1.331548,
          "E6": 0.013119,
          "E2": 0.662494,
          "E15": 0.013119,
          "E70": 0.013119,
          "E1": 0.332559,
          "Confidential Compute Encryption": 0.00021,
          "Snapshots": 1.239717,
          "Disk Transactions": 0.022171
        },
        "standard-hdd": {
          "S15": 0.00328,
          "S80": 0.00328,
          "S30": 0.00328,
          "S70": 0.00328,
          "S10": 0.00328,
          "S4": 0.00328,
          "S20": 0.00328,
          "Disk Transactions": 0.005543,
          "S50": 0.00328,
          "S6": 0.00328,
          "S60": 0.00328,
          "S40": 0.00328,
          "Snapshots": 0.426358,
          "Standard HDD Managed Disks - Confidential Compute Encryption": 8.5e-05
        }
      }
    }
  }
}